[
    {
        "id": "abrigo-01",
        "titulo": "Producto 01",
        "imagen": "./img/abrigos/01.jpg",
        "categoria": {
            "nombre": "Productos",
            "id": "abrigos"
        },
        "precio": 1000
    },
    {
        "id": "abrigo-02",
        "titulo": "Producto 02",
        "imagen": "./img/abrigos/02.jpg",
        "categoria": {
            "nombre": "Productos",
            "id": "abrigos"
        },
        "precio": 1000
    },
    {
        "id": "abrigo-03",
        "titulo": "Producto 03",
        "imagen": "./img/abrigos/03.jpg",
        "categoria": {
            "nombre": "Productos",
            "id": "abrigos"
        },
        "precio": 1000
    },
    {
        "id": "Producto-04",
        "titulo": "Producto 04",
        "imagen": "./img/abrigos/04.jpg",
        "categoria": {
            "nombre": "Productos",
            "id": "abrigos"
        },
        "precio": 1000
    },
    {
        "id": "abrigo-05",
        "titulo": "Producto 05",
        "imagen": "./img/abrigos/05.jpg",
        "categoria": {
            "nombre": "Productos",
            "id": "abrigos"
        },
        "precio": 1000
    },
    {
        "id": "camiseta-01",
        "titulo": "Producto 01",
        "imagen": "./img/camisetas/01.jpg",
        "categoria": {
            "nombre": "Productos",
            "id": "camisetas"
        },
        "precio": 1000
    },
    {
        "id": "camiseta-02",
        "titulo": "Producto 02",
        "imagen": "./img/camisetas/02.jpg",
        "categoria": {
            "nombre": "Productos",
            "id": "camisetas"
        },
        "precio": 1000
    },
    {
        "id": "camiseta-03",
        "titulo": "Producto 03",
        "imagen": "./img/camisetas/03.jpg",
        "categoria": {
            "nombre": "Productos",
            "id": "camisetas"
        },
        "precio": 1000
    },
    {
        "id": "camiseta-04",
        "titulo": "Producto 04",
        "imagen": "./img/camisetas/04.jpg",
        "categoria": {
            "nombre": "Productos",
            "id": "camisetas"
        },
        "precio": 1000
    },
    {
        "id": "camiseta-05",
        "titulo": "Producto 05",
        "imagen": "./img/camisetas/05.jpg",
        "categoria": {
            "nombre": "Productos",
            "id": "camisetas"
        },
        "precio": 1000
    },
    {
        "id": "camiseta-06",
        "titulo": "Producto 06",
        "imagen": "./img/camisetas/06.jpg",
        "categoria": {
            "nombre": "Productos",
            "id": "camisetas"
        },
        "precio": 1000
    },
    {
        "id": "camiseta-07",
        "titulo": "Producto 07",
        "imagen": "./img/camisetas/07.jpg",
        "categoria": {
            "nombre": "Productos",
            "id": "camisetas"
        },
        "precio": 1000
    },
    {
        "id": "camiseta-08",
        "titulo": "Producto 08",
        "imagen": "./img/camisetas/08.jpg",
        "categoria": {
            "nombre": "Productos",
            "id": "camisetas"
        },
        "precio": 1000
    },
    {
        "id": "pantalon-01",
        "titulo": "Producto 01",
        "imagen": "./img/pantalones/01.jpg",
        "categoria": {
            "nombre": "Productos",
            "id": "pantalones"
        },
        "precio": 1000
    },
    {
        "id": "pantalon-02",
        "titulo": "Producto 02",
        "imagen": "./img/pantalones/02.jpg",
        "categoria": {
            "nombre": "Productos",
            "id": "pantalones"
        },
        "precio": 1000
    },
    {
        "id": "pantalon-03",
        "titulo": "Producto 03",
        "imagen": "./img/pantalones/03.jpg",
        "categoria": {
            "nombre": "Productos",
            "id": "pantalones"
        },
        "precio": 1000
    },
    {
        "id": "pantalon-04",
        "titulo": "Producto 04",
        "imagen": "./img/pantalones/04.jpg",
        "categoria": {
            "nombre": "Productos",
            "id": "pantalones"
        },
        "precio": 1000
    },
    {
        "id": "pantalon-05",
        "titulo": "Producto 05",
        "imagen": "./img/pantalones/05.jpg",
        "categoria": {
            "nombre": "Productos",
            "id": "pantalones"
        },
        "precio": 1000
    }
]